celeste_gradium/__init__.py
celeste_gradium/py.typed
celeste_gradium/text_to_speech/__init__.py
celeste_gradium/text_to_speech/client.py
celeste_gradium/text_to_speech/config.py
celeste_gradium/text_to_speech/parameters.py
celeste_gradium-0.3.6.dist-info/METADATA
celeste_gradium-0.3.6.dist-info/WHEEL
celeste_gradium-0.3.6.dist-info/RECORD
